wavescli/__init__.py
wavescli/__main__.py
wavescli/apiclient.py
wavescli/awsadapter.py
wavescli/cli.py
wavescli/config.py
wavescli/downloader.py
wavescli/logger.py
wavescli/waves.py
wavescli-0.0.43.dist-info/METADATA
wavescli-0.0.43.dist-info/RECORD
wavescli-0.0.43.dist-info/WHEEL
wavescli-0.0.43.dist-info/entry_points.txt
wavescli-0.0.43.dist-info/top_level.txt
